md2gdocs-1.0.0.dist-info/METADATA
md2gdocs-1.0.0.dist-info/WHEEL
md2gdocs-1.0.0.dist-info/entry_points.txt
md2gdocs/__init__.py
md2gdocs/upload.py
md2gdocs-1.0.0.dist-info/RECORD
