Metadata-Version: 2.1
Name: md2gdocs
Version: 1.0.0
Summary: Tool to upload markdown to Google Drive/Docs.
Home-page: https://gitlab.com/wryfi/md2gdocs
Author-Email: Christian Haumesser <chris.haumesser@gmail.com>
License: MIT
Classifier: Programming Language :: Python :: 3
Classifier: Programming Language :: Python :: 3.10
Classifier: Programming Language :: Python :: 3.11
Classifier: Programming Language :: Python :: 3.12
Classifier: License :: OSI Approved :: MIT License
Project-URL: Homepage, https://gitlab.com/wryfi/md2gdocs
Project-URL: Documentation, https://gitlab.com/wryfi/md2gdocs
Project-URL: Repository, https://gitlab.com/wryfi/md2gdocs
Requires-Python: >=3.10
Requires-Dist: google-api-python-client
Requires-Dist: google-auth-httplib2
Requires-Dist: google-auth-oauthlib
Requires-Dist: cfitall
Requires-Dist: python-frontmatter
Requires-Dist: markdown
